README.md
setup.cfg
setup.py
log_viewer/__init__.py
log_viewer/main.py
log_viewer/settings.py
log_viewer/utils.py
log_viewer.egg-info/PKG-INFO
log_viewer.egg-info/SOURCES.txt
log_viewer.egg-info/dependency_links.txt
log_viewer.egg-info/entry_points.txt
log_viewer.egg-info/not-zip-safe
log_viewer.egg-info/requires.txt
log_viewer.egg-info/top_level.txt
log_viewer/api/__init__.py
log_viewer/api/v0/__init__.py
log_viewer/api/v0/logs.py
log_viewer/controllers/__init__.py
log_viewer/controllers/exceptions.py
log_viewer/controllers/log_controller.py
log_viewer/controllers/session_controller.py