Metadata-Version: 2.1
Name: log-viewer
Version: 0.1.0
Summary: Project that exposes the logs.
Home-page: https://github.com/moonrollersoft/log-viewer/
Author: moonrollersoft
Author-email: moonrollersoft@gmail.com
License: MIT
Download-URL: https://github.com/moonrollersoft/log-viewer/archive/v0.1.0.tar.gz
Platform: UNKNOWN
Classifier: Development Status :: 4 - Beta
Classifier: Intended Audience :: Developers
Classifier: License :: OSI Approved :: MIT License
Classifier: Programming Language :: Python :: 3.6
Classifier: Programming Language :: Python :: 3.7
Classifier: Programming Language :: Python :: 3.8
Classifier: Programming Language :: Python :: 3.9
Requires-Python: >=3.6
